plp_antispam_rust-1.0.3.dist-info/METADATA
plp_antispam_rust-1.0.3.dist-info/WHEEL
plpas/__init__.py
plpas/plpas.abi3.so
plp_antispam_rust-1.0.3.dist-info/RECORD
