Metadata-Version: 2.4
Name: plp-antispam-rust
Version: 1.0.3
Classifier: Programming Language :: Rust
Classifier: Programming Language :: Python :: Implementation :: CPython
Classifier: Topic :: Communications :: Email :: Filters
Classifier: Topic :: Scientific/Engineering :: Artificial Intelligence
Summary: Fast Rust-based anti-spam inference engine for email classification
Author: Paul Lucian Pinzariu
License: MIT
Requires-Python: >=3.9
